[
  {
    "id": 1,
    "title": "Two Sum",
    "difficulty": "Easy",
    "url": "https://leetcode.com/problems/two-sum/",
    "tags": ["Array", "Hash Table"],
    "patterns": ["Two Pointers", "Hash Map"],
    "companies": ["Google", "Amazon", "Microsoft", "Facebook"],
    "dateAdded": "2023-01-01",
    "description": "Given an array of integers nums and an integer target, return indices of the two numbers such that they add up to target."
  },
  {
    "id": 3,
    "title": "Longest Substring Without Repeating Characters",
    "difficulty": "Medium",
    "url": "https://leetcode.com/problems/longest-substring-without-repeating-characters/",
    "tags": ["Hash Table", "String", "Sliding Window"],
    "patterns": ["Sliding Window", "Hash Map"],
    "companies": ["Amazon", "Microsoft", "Bloomberg"],
    "dateAdded": "2023-01-03",
    "description": "Given a string s, find the length of the longest substring without repeating characters."
  },
  {
    "id": 4,
    "title": "Median of Two Sorted Arrays",
    "difficulty": "Hard",
    "url": "https://leetcode.com/problems/median-of-two-sorted-arrays/",
    "tags": ["Array", "Binary Search", "Divide and Conquer"],
    "patterns": ["Binary Search"],
    "companies": ["Google", "Microsoft", "Apple"],
    "dateAdded": "2023-01-04",
    "description": "Given two sorted arrays nums1 and nums2 of size m and n respectively, return the median of the two sorted arrays."
  },
  {
    "id": 121,
    "title": "Best Time to Buy and Sell Stock",
    "difficulty": "Easy",
    "url": "https://leetcode.com/problems/best-time-to-buy-and-sell-stock/",
    "tags": ["Array", "Dynamic Programming"],
    "patterns": ["Kadane's Algorithm", "DP"],
    "companies": ["Amazon", "Microsoft", "Facebook", "Apple"],
    "dateAdded": "2023-02-15",
    "description": "You are given an array prices where prices[i] is the price of a given stock on the ith day."
  },
  {
    "id": 200,
    "title": "Number of Islands",
    "difficulty": "Medium",
    "url": "https://leetcode.com/problems/number-of-islands/",
    "tags": ["Array", "Depth-First Search", "Breadth-First Search", "Union Find", "Matrix"],
    "patterns": ["DFS", "BFS", "Union Find"],
    "companies": ["Amazon", "Microsoft", "Facebook", "Google"],
    "dateAdded": "2023-03-01",
    "description": "Given an m x n 2D binary grid grid which represents a map of '1's (land) and '0's (water), return the number of islands."
  },
  {
    "id": 206,
    "title": "Reverse Linked List",
    "difficulty": "Easy",
    "url": "https://leetcode.com/problems/reverse-linked-list/",
    "tags": ["Linked List", "Recursion"],
    "patterns": ["Two Pointers", "Recursion"],
    "companies": ["Amazon", "Microsoft", "Apple", "Facebook"],
    "dateAdded": "2023-03-05",
    "description": "Given the head of a singly linked list, reverse the list, and return the reversed list."
  },
  {
    "id": 238,
    "title": "Product of Array Except Self",
    "difficulty": "Medium",
    "url": "https://leetcode.com/problems/product-of-array-except-self/",
    "tags": ["Array", "Prefix Sum"],
    "patterns": ["Prefix Sum"],
    "companies": ["Amazon", "Microsoft", "Facebook", "Apple"],
    "dateAdded": "2023-03-10",
    "description": "Given an integer array nums, return an array answer such that answer[i] is equal to the product of all the elements of nums except nums[i]."
  },
  {
    "id": 15,
    "title": "3Sum",
    "difficulty": "Medium",
    "url": "https://leetcode.com/problems/3sum/",
    "tags": ["Array", "Two Pointers", "Sorting"],
    "patterns": ["Two Pointers", "Sorting"],
    "companies": ["Amazon", "Microsoft", "Facebook", "Adobe"],
    "dateAdded": "2023-04-01",
    "description": "Given an integer array nums, return all the triplets [nums[i], nums[j], nums[k]] such that i != j, i != k, and j != k, and nums[i] + nums[j] + nums[k] == 0."
  },
  {
    "id": 53,
    "title": "Maximum Subarray",
    "difficulty": "Medium",
    "url": "https://leetcode.com/problems/maximum-subarray/",
    "tags": ["Array", "Divide and Conquer", "Dynamic Programming"],
    "patterns": ["Kadane's Algorithm", "DP"],
    "companies": ["Amazon", "Microsoft", "LinkedIn", "Bloomberg"],
    "dateAdded": "2023-04-15",
    "description": "Given an integer array nums, find the contiguous subarray (containing at least one number) which has the largest sum and return its sum."
  },
  {
    "id": 70,
    "title": "Climbing Stairs",
    "difficulty": "Easy",
    "url": "https://leetcode.com/problems/climbing-stairs/",
    "tags": ["Math", "Dynamic Programming", "Memoization"],
    "patterns": ["DP", "Fibonacci"],
    "companies": ["Amazon", "Adobe", "Apple"],
    "dateAdded": "2023-05-01",
    "description": "You are climbing a staircase. It takes n steps to reach the top. Each time you can either climb 1 or 2 steps. In how many distinct ways can you climb to the top?"
  }
]